garble/__init__.py
garble/base.py
garble-0.0.3.dist-info/LICENSE
garble-0.0.3.dist-info/METADATA
garble-0.0.3.dist-info/WHEEL
garble-0.0.3.dist-info/top_level.txt
garble-0.0.3.dist-info/RECORD
