Metadata-Version: 2.1
Name: garble
Version: 0.0.3
Summary: Make bags of words and do stuff with them for make benefit
Home-page: https://github.com/thorwhalen/garble
Author: Thor Whalen
License: apache-2.0
Platform: any
Requires-Dist: numpy
Requires-Dist: scikit-learn
Requires-Dist: wordcloud
Requires-Dist: py2store
